django_shibboleth/__init__.py
django_shibboleth/decorators.py
django_shibboleth/forms.py
django_shibboleth/models.py
django_shibboleth/signals.py
django_shibboleth/urls.py
django_shibboleth/utils.py
django_shibboleth/views.py
django_shibboleth/templates/shibboleth/attribute_error.html
django_shibboleth/templates/shibboleth/meta.html
django_shibboleth/templates/shibboleth/register.html
loris/__init__.py
loris/authorizer.py
loris/constants.py
loris/identifiers.py
loris/img.py
loris/img_info.py
loris/jp2_extractor.py
loris/loris_exception.py
loris/parameters.py
loris/resolver.py
loris/transforms.py
loris/user_commands.py
loris/utils.py
loris/webapp.py
mdid-3.8.1.dist-info/licenses/LICENSE
rooibos/RELEASE-VERSION
rooibos/__init__.py
rooibos/__main__.py
rooibos/celeryapp.py
rooibos/context_processors.py
rooibos/middleware.py
rooibos/urls.py
rooibos/version.py
rooibos/wsgi.py
rooibos/access/__init__.py
rooibos/access/admin.py
rooibos/access/functions.py
rooibos/access/middleware.py
rooibos/access/models.py
rooibos/access/tests.py
rooibos/access/urls.py
rooibos/access/views.py
rooibos/access/management/__init__.py
rooibos/access/management/commands/__init__.py
rooibos/access/management/commands/ip_range_access.py
rooibos/access/migrations/0001_initial.py
rooibos/access/migrations/0002_auto_20191209_1108.py
rooibos/access/migrations/0003_auto_20220119_1055.py
rooibos/access/migrations/__init__.py
rooibos/access/templates/access_effective_permissions.html
rooibos/access/templates/access_effective_permissions_form.html
rooibos/access/templates/access_modify_permissions.html
rooibos/access/templates/access_permissions_display.html
rooibos/access/templates/unsafe_logout.html
rooibos/access/templatetags/__init__.py
rooibos/access/templatetags/access_control.py
rooibos/api/__init__.py
rooibos/api/models.py
rooibos/api/urls.py
rooibos/api/views.py
rooibos/auth/__init__.py
rooibos/auth/baseauth.py
rooibos/auth/ldapauth.py
rooibos/auth/mailauth.py
rooibos/auth/middleware.py
rooibos/data/__init__.py
mdid-3.8.1.dist-info/METADATA
mdid-3.8.1.dist-info/WHEEL
mdid-3.8.1.dist-info/entry_points.txt
mdid-3.8.1.dist-info/top_level.txt
mdid-3.8.1.dist-info/RECORD
