Metadata-Version: 2.4
Name: mdid
Version: 3.8.1
Summary: MDID is a digital media management system
Home-page: https://mdid.org
Author: vrcHost LLC
Author-email: info@vrchost.com
License: GPL
Platform: Linux
Platform: Windows
Requires-Python: >=3.8
License-File: LICENSE
Requires-Dist: Celery==5.2.7
Requires-Dist: Django==3.2.23
Requires-Dist: amqp==5.0.9
Requires-Dist: attrs==21.4.0
Requires-Dist: b2sdk==1.14.1
Requires-Dist: beautifulsoup4==4.10.0
Requires-Dist: bleach-allowlist==1.0.3
Requires-Dist: bleach==4.1.0
Requires-Dist: boto3==1.20.38
Requires-Dist: cached-property==1.5.2
Requires-Dist: click-didyoumean==0.3.0
Requires-Dist: click-plugins==1.1.1
Requires-Dist: click-repl==0.2.0
Requires-Dist: click==8.0.3
Requires-Dist: configobj==5.0.9
Requires-Dist: cryptography==44.0.1
Requires-Dist: django-appconf==1.0.5
Requires-Dist: django-cas-ng==4.3.0
Requires-Dist: django-celery-results==2.4.0
Requires-Dist: django-compressor==3.1
Requires-Dist: django-contrib-comments==2.1.0
Requires-Dist: django-cors-headers==3.11.0
Requires-Dist: django-extensions==3.1.5
Requires-Dist: django-pagination==1.0.7
Requires-Dist: django-ranged-fileresponse==0.1.2
Requires-Dist: django-storages==1.12.3
Requires-Dist: django-tagging==0.5.0
Requires-Dist: flake8==4.0.1
Requires-Dist: flake8-docstrings==1.6.0
Requires-Dist: flake8-todo==0.7
Requires-Dist: flickrapi==2.4.0
Requires-Dist: gunicorn==23.0.0
Requires-Dist: importlib-metadata==4.11.4
Requires-Dist: ipaddr==2.2.0
Requires-Dist: kombu==5.2.3
Requires-Dist: markdown==3.2.2
Requires-Dist: pika==1.2.0
Requires-Dist: pillow>=11.3.0
Requires-Dist: prompt-toolkit==3.0.24
Requires-Dist: pycryptodome==3.12.0
Requires-Dist: pymysql==1.1.1
Requires-Dist: pypdf==5.9.0
Requires-Dist: python-ldap<3.5.0,>=3.4.0
Requires-Dist: python-memcached==1.62
Requires-Dist: python-pptx==0.6.21
Requires-Dist: reportlab==4.0.8
Requires-Dist: requests==2.32.4
Requires-Dist: setuptools>=78.1.1
Requires-Dist: sqlparse==0.5.0
Requires-Dist: vine==5.0.0
Requires-Dist: wcwidth==0.2.5
Requires-Dist: werkzeug==3.0.6
Requires-Dist: wfastcgi==3.0.0
Requires-Dist: wheel>=0.38.1
Dynamic: author
Dynamic: author-email
Dynamic: description
Dynamic: home-page
Dynamic: license
Dynamic: license-file
Dynamic: platform
Dynamic: requires-dist
Dynamic: requires-python
Dynamic: summary
